{"neotest-vim-test": {"commit": "07f25ab"}, "nvim-dap": {"commit": "6f2ea9e"}, "material.nvim": {"commit": "0560aba"}, "FixCursorHold.nvim": {"commit": "70a9516"}, "vim-signature": {"commit": "6bc3dd1"}, "neotest-jest": {"commit": "2051686"}, "packer.nvim": {"commit": "dac4088"}, "nvim-notify": {"commit": "b005821"}, "vim-surround": {"commit": "3d188ed"}, "nvim-lspconfig": {"commit": "42ca8ce"}, "playground": {"commit": "8a887bc"}, "nvim-dap-go": {"commit": "8aa9e7e"}, "vim-bufkill": {"commit": "3113181"}, "virt-column.nvim": {"commit": "36fa3be"}, "nvim-treesitter": {"commit": "0cb637ca"}, "nvim-treesitter-endwise": {"commit": "0cf4601"}, "vim-tmux-navigator": {"commit": "41ea9d2"}, "mason-lspconfig.nvim": {"commit": "c29f9a9"}, "lualine.nvim": {"commit": "fffbcb8"}, "cmp-cmdline": {"commit": "23c51b2"}, "tabline-framework.nvim": {"commit": "dae4732"}, "aerial.nvim": {"commit": "7e2fef6"}, "cmp-nvim-lsp": {"commit": "5922477"}, "cmp_luasnip": {"commit": "1809552"}, "neotest-go": {"commit": "981406c"}, "vim-test": {"commit": "c6e5d24"}, "vim-fugitive": {"commit": "5b0b138"}, "neotest-python": {"commit": "e53920d"}, "dressing.nvim": {"commit": "4436d6f"}, "startup.nvim": {"commit": "b060480"}, "lspkind-nvim": {"commit": "c68b3a0"}, "neo-tree.nvim": {"commit": "73a90f6"}, "telescope.nvim": {"commit": "e960efa"}, "trouble.nvim": {"commit": "897542f"}, "nvim-ts-context-commentstring": {"commit": "32d9627"}, "lsp_signature.nvim": {"commit": "1979f11"}, "Comment.nvim": {"commit": "45dc21a"}, "mason.nvim": {"commit": "e7303a1"}, "nvim-autopairs": {"commit": "03580d7"}, "vim-dispatch": {"commit": "00e77d9"}, "LuaSnip": {"commit": "5570fd7"}, "toggle-lsp-diagnostics.nvim": {"commit": "a783974"}, "nvim-dap-ui": {"commit": "54365d2"}, "lsp-inlayhints.nvim": {"commit": "84ca3ab"}, "nvim-web-devicons": {"commit": "05e1072"}, "nvim-dap-virtual-text": {"commit": "2971ce3"}, "nui.nvim": {"commit": "4939282"}, "neotest": {"commit": "de2f68f"}, "vim-abolish": {"commit": "3f0c8fa"}, "nvim-window-picker": {"commit": "5902827"}, "fidget.nvim": {"commit": "44585a0"}, "null-ls.nvim": {"commit": "b26851b"}, "vim-projectionist": {"commit": "558013b"}, "nvim-dap-python": {"commit": "d4400d0"}, "plenary.nvim": {"commit": "4b7e520"}, "nvim-cmp": {"commit": "e55033f"}, "vim-floaterm": {"commit": "280b34a"}, "vim-devicons": {"commit": "71f239a"}, "cmp-path": {"commit": "91ff86c"}, "cmp-buffer": {"commit": "3022dbc"}}
